dmsan/__init__.py
dmsan/_ahp.py
dmsan/_location.py
dmsan/_mcda.py
dmsan/utils.py
dmsan/biogenic_refinery/__init__.py
dmsan/biogenic_refinery/sys_simulation.py
dmsan/bwaise/README.rst
dmsan/bwaise/__init__.py
dmsan/bwaise/improvements.py
dmsan/bwaise/ks_result_analysis.py
dmsan/bwaise/line_graph.py
dmsan/bwaise/mcda.py
dmsan/bwaise/spearman_result_analysis.py
dmsan/bwaise/sys_simulation.py
dmsan/comparison/__init__.py
dmsan/comparison/analyses.py
dmsan/comparison/mcda.py
dmsan/comparison/plotting.py
dmsan/comparison/sys_sim_sensitivity.py
dmsan/comparison/sys_sim_uncertainty.py
dmsan/comparison/data/country_specific_inputs.csv
dmsan/comparison/data/country_specific_inputs_gates.csv
dmsan/data/criteria_and_indicators.xlsx
dmsan/data/location.xlsx
dmsan/new_generator/__init__.py
dmsan/new_generator/sys_simulation.py
dmsan/reclaimer/__init__.py
dmsan/reclaimer/sys_simulation.py
dmsan-0.1.0.dist-info/LICENSE.txt
dmsan-0.1.0.dist-info/METADATA
dmsan-0.1.0.dist-info/WHEEL
dmsan-0.1.0.dist-info/top_level.txt
dmsan-0.1.0.dist-info/RECORD
